src/ucyph/__init__.py
src/ucyph/ciphers.py
src/ucyph/ucyph.py
src/ucyph/utils.py
ucyph-0.2.2.dist-info/LICENSE
ucyph-0.2.2.dist-info/METADATA
ucyph-0.2.2.dist-info/WHEEL
ucyph-0.2.2.dist-info/entry_points.txt
ucyph-0.2.2.dist-info/top_level.txt
ucyph-0.2.2.dist-info/RECORD
