Metadata-Version: 2.1
Name: ucyph
Version: 0.2.2
Summary: A command-line tool for encrypting and decrypting strings using various ciphers
Author-email: Adam Slay <adamslay11@gmail.com>
License: MIT
Project-URL: Homepage, https://github.com/AdamSlay/ucyph
Classifier: Programming Language :: Python :: 3
Classifier: License :: OSI Approved :: MIT License
Classifier: Operating System :: OS Independent
License-File: LICENSE
